{
	"animations": [
		{
			"offsets": [
				23,
				-9
			],
			"loop": false,
			"anim": "singLEFT",
			"fps": 24,
			"name": "BF NOTE LEFT0",
			"indices": []
		},
		{
			"offsets": [
				-30,
				-68
			],
			"loop": false,
			"anim": "singDOWN",
			"fps": 24,
			"name": "BF NOTE DOWN0",
			"indices": []
		},
		{
			"offsets": [
				-48,
				11
			],
			"loop": false,
			"anim": "singUP",
			"fps": 24,
			"name": "BF NOTE UP0",
			"indices": []
		},
		{
			"offsets": [
				-15,
				-17
			],
			"loop": false,
			"anim": "singRIGHT",
			"fps": 24,
			"name": "BF NOTE RIGHT0",
			"indices": []
		},
		{
			"offsets": [
				12,
				12
			],
			"loop": false,
			"anim": "singLEFTmiss",
			"fps": 24,
			"name": "BF NOTE LEFT MISS",
			"indices": []
		},
		{
			"offsets": [
				-18,
				-41
			],
			"loop": false,
			"anim": "singDOWNmiss",
			"fps": 24,
			"name": "BF NOTE DOWN MISS",
			"indices": []
		},
		{
			"offsets": [
				-45,
				7
			],
			"loop": false,
			"anim": "singUPmiss",
			"fps": 24,
			"name": "BF NOTE UP MISS",
			"indices": []
		},
		{
			"offsets": [
				-18,
				20
			],
			"loop": false,
			"anim": "singRIGHTmiss",
			"fps": 24,
			"name": "BF NOTE RIGHT MISS",
			"indices": []
		},
		{
			"offsets": [
				17,
				-5
			],
			"loop": false,
			"anim": "hey",
			"fps": 24,
			"name": "BF HEY",
			"indices": []
		},
		{
			"offsets": [
				-3,
				-1
			],
			"indices": [],
			"fps": 24,
			"anim": "idle",
			"loop": true,
			"name": "BF idle dance"
		}
	],
	"no_antialiasing": false,
	"image": "bambi/bambiChristmas",
	"position": [
		0,
		350
	],
	"healthicon": "bevel_a9",
	"flip_x": true,
	"healthbar_colors": [
		0,
		255,
		0
	],
	"camera_position": [
		0,
		0
	],
	"sing_duration": 4,
	"scale": 1
}